mandrill.py
mandrill_hypocampus-1.0.58.data/scripts/mandrill
mandrill_hypocampus-1.0.58.data/scripts/sendmail.mandrill
mandrill_hypocampus-1.0.58.dist-info/LICENSE
mandrill_hypocampus-1.0.58.dist-info/METADATA
mandrill_hypocampus-1.0.58.dist-info/WHEEL
mandrill_hypocampus-1.0.58.dist-info/top_level.txt
mandrill_hypocampus-1.0.58.dist-info/RECORD
