Metadata-Version: 2.1
Name: mandrill-hypocampus
Version: 1.0.58
Summary: A CLI client and Python API library for the Mandrill email as a service platform.
Home-page: https://gitlab.com/hypocampus/mandrill-api-python
Author: Mandrill Devs & hypocampus
Author-email: magnus.odman@gmail.com
License: Apache-2.0
Keywords: mandrill email api
Platform: UNKNOWN
Classifier: Development Status :: 4 - Beta
Classifier: Environment :: Console
Classifier: Intended Audience :: Developers
Classifier: Intended Audience :: System Administrators
Classifier: License :: OSI Approved :: Apache Software License
Classifier: Topic :: Communications :: Email
Requires-Dist: docopt (>=0.6.2)
Requires-Dist: requests (>=2.21.0)
